{"id":"china_database","name":"China Database","server":"gpu104","source":"/data3/kow/CM_China_Database/log/all_process","mirror":"log_mirror/china_database","status":"error","daysOld":null,"latestDate":"2026-06-21","latestFile":"2026/06/nohup-2026-06-21.out","latestLine":"Total running time: .04 hours","fileCount":14,"dateCount":14,"totalBytes":102158,"totalSize":"99.8 KB","latestErrors":15,"latestWarnings":3,"dates":[{"date":"2026-06-21","count":1,"status":"error","errors":15,"warnings":3,"latestModified":"2026-06-21 08:02:34","mtime":1782000154.8715563},{"date":"2026-06-20","count":1,"status":"error","errors":15,"warnings":3,"latestModified":"2026-06-20 08:02:31","mtime":1781913751.6264038},{"date":"2026-06-19","count":1,"status":"error","errors":15,"warnings":3,"latestModified":"2026-06-19 08:02:35","mtime":1781827355.4440753},{"date":"2026-06-18","count":1,"status":"error","errors":15,"warnings":3,"latestModified":"2026-06-18 08:02:27","mtime":1781740947.06884},{"date":"2026-06-17","count":1,"status":"error","errors":15,"warnings":3,"latestModified":"2026-06-17 08:02:35","mtime":1781654555.0497155},{"date":"2026-06-16","count":1,"status":"error","errors":75,"warnings":3,"latestModified":"2026-06-16 08:05:40","mtime":1781568340.057379},{"date":"2026-06-15","count":1,"status":"error","errors":15,"warnings":3,"latestModified":"2026-06-15 08:02:28","mtime":1781481748.704178},{"date":"2026-06-14","count":1,"status":"error","errors":15,"warnings":3,"latestModified":"2026-06-14 08:02:35","mtime":1781395355.856261},{"date":"2026-06-13","count":1,"status":"error","errors":15,"warnings":3,"latestModified":"2026-06-13 08:02:35","mtime":1781308955.1555297},{"date":"2026-06-12","count":1,"status":"error","errors":15,"warnings":3,"latestModified":"2026-06-12 08:02:35","mtime":1781222555.5599177},{"date":"2026-06-11","count":1,"status":"error","errors":15,"warnings":3,"latestModified":"2026-06-11 08:02:32","mtime":1781136152.929191},{"date":"2026-06-10","count":1,"status":"error","errors":15,"warnings":3,"latestModified":"2026-06-10 08:02:30","mtime":1781049750.972124},{"date":"2026-06-09","count":1,"status":"error","errors":75,"warnings":3,"latestModified":"2026-06-09 08:05:39","mtime":1780963539.3107998},{"date":"2026-06-08","count":1,"status":"error","errors":15,"warnings":3,"latestModified":"2026-06-08 08:02:35","mtime":1780876955.9705102}],"logsByDate":{"2026-06-09":[{"path":"2026/06/nohup-2026-06-09.out","name":"nohup-2026-06-09.out","date":"2026-06-09","status":"error","size":16374,"sizeLabel":"16.0 KB","mtime":1780963539.3107998,"modified":"2026-06-09 08:05:39","errors":75,"warnings":3,"okSignals":10,"lastLine":"Total running time: .09 hours","dataPath":"data/logs/china_database/b357d439da2991f1.json"}],"2026-06-21":[{"path":"2026/06/nohup-2026-06-21.out","name":"nohup-2026-06-21.out","date":"2026-06-21","status":"error","size":5789,"sizeLabel":"5.7 KB","mtime":1782000154.8715563,"modified":"2026-06-21 08:02:34","errors":15,"warnings":3,"okSignals":10,"lastLine":"Total running time: .04 hours","dataPath":"data/logs/china_database/37e7618ef85af9f5.json"}],"2026-06-15":[{"path":"2026/06/nohup-2026-06-15.out","name":"nohup-2026-06-15.out","date":"2026-06-15","status":"error","size":5781,"sizeLabel":"5.6 KB","mtime":1781481748.704178,"modified":"2026-06-15 08:02:28","errors":15,"warnings":3,"okSignals":10,"lastLine":"Total running time: .04 hours","dataPath":"data/logs/china_database/607fd122210bb1f4.json"}],"2026-06-11":[{"path":"2026/06/nohup-2026-06-11.out","name":"nohup-2026-06-11.out","date":"2026-06-11","status":"error","size":5789,"sizeLabel":"5.7 KB","mtime":1781136152.929191,"modified":"2026-06-11 08:02:32","errors":15,"warnings":3,"okSignals":10,"lastLine":"Total running time: .04 hours","dataPath":"data/logs/china_database/f7485517f7de6b2b.json"}],"2026-06-16":[{"path":"2026/06/nohup-2026-06-16.out","name":"nohup-2026-06-16.out","date":"2026-06-16","status":"error","size":16374,"sizeLabel":"16.0 KB","mtime":1781568340.057379,"modified":"2026-06-16 08:05:40","errors":75,"warnings":3,"okSignals":10,"lastLine":"Total running time: .09 hours","dataPath":"data/logs/china_database/06ff92eb9ca0451e.json"}],"2026-06-08":[{"path":"2026/06/nohup-2026-06-08.out","name":"nohup-2026-06-08.out","date":"2026-06-08","status":"error","size":5788,"sizeLabel":"5.7 KB","mtime":1780876955.9705102,"modified":"2026-06-08 08:02:35","errors":15,"warnings":3,"okSignals":10,"lastLine":"Total running time: .04 hours","dataPath":"data/logs/china_database/01bf5a9c22ded5da.json"}],"2026-06-14":[{"path":"2026/06/nohup-2026-06-14.out","name":"nohup-2026-06-14.out","date":"2026-06-14","status":"error","size":5781,"sizeLabel":"5.6 KB","mtime":1781395355.856261,"modified":"2026-06-14 08:02:35","errors":15,"warnings":3,"okSignals":10,"lastLine":"Total running time: .04 hours","dataPath":"data/logs/china_database/030f6a90d7e26596.json"}],"2026-06-10":[{"path":"2026/06/nohup-2026-06-10.out","name":"nohup-2026-06-10.out","date":"2026-06-10","status":"error","size":5782,"sizeLabel":"5.6 KB","mtime":1781049750.972124,"modified":"2026-06-10 08:02:30","errors":15,"warnings":3,"okSignals":10,"lastLine":"Total running time: .04 hours","dataPath":"data/logs/china_database/f12071d9c828d378.json"}],"2026-06-13":[{"path":"2026/06/nohup-2026-06-13.out","name":"nohup-2026-06-13.out","date":"2026-06-13","status":"error","size":5789,"sizeLabel":"5.7 KB","mtime":1781308955.1555297,"modified":"2026-06-13 08:02:35","errors":15,"warnings":3,"okSignals":10,"lastLine":"Total running time: .04 hours","dataPath":"data/logs/china_database/cb3e71bd7e96cf85.json"}],"2026-06-12":[{"path":"2026/06/nohup-2026-06-12.out","name":"nohup-2026-06-12.out","date":"2026-06-12","status":"error","size":5788,"sizeLabel":"5.7 KB","mtime":1781222555.5599177,"modified":"2026-06-12 08:02:35","errors":15,"warnings":3,"okSignals":10,"lastLine":"Total running time: .04 hours","dataPath":"data/logs/china_database/fcf0ae69e0b85b39.json"}],"2026-06-18":[{"path":"2026/06/nohup-2026-06-18.out","name":"nohup-2026-06-18.out","date":"2026-06-18","status":"error","size":5781,"sizeLabel":"5.6 KB","mtime":1781740947.06884,"modified":"2026-06-18 08:02:27","errors":15,"warnings":3,"okSignals":10,"lastLine":"Total running time: .04 hours","dataPath":"data/logs/china_database/dea513030873bef7.json"}],"2026-06-20":[{"path":"2026/06/nohup-2026-06-20.out","name":"nohup-2026-06-20.out","date":"2026-06-20","status":"error","size":5781,"sizeLabel":"5.6 KB","mtime":1781913751.6264038,"modified":"2026-06-20 08:02:31","errors":15,"warnings":3,"okSignals":10,"lastLine":"Total running time: .04 hours","dataPath":"data/logs/china_database/a6cdde8fea143001.json"}],"2026-06-17":[{"path":"2026/06/nohup-2026-06-17.out","name":"nohup-2026-06-17.out","date":"2026-06-17","status":"error","size":5780,"sizeLabel":"5.6 KB","mtime":1781654555.0497155,"modified":"2026-06-17 08:02:35","errors":15,"warnings":3,"okSignals":10,"lastLine":"Total running time: .04 hours","dataPath":"data/logs/china_database/874bf9f413488461.json"}],"2026-06-19":[{"path":"2026/06/nohup-2026-06-19.out","name":"nohup-2026-06-19.out","date":"2026-06-19","status":"error","size":5781,"sizeLabel":"5.6 KB","mtime":1781827355.4440753,"modified":"2026-06-19 08:02:35","errors":15,"warnings":3,"okSignals":10,"lastLine":"Total running time: .04 hours","dataPath":"data/logs/china_database/3801caf0dfb5b7ed.json"}]},"dateOffset":0,"loadedDateCount":14,"hasMoreDates":false}