{"project":"china_database","path":"2026/07/nohup-2026-07-07.md","name":"nohup-2026-07-07.md","lines":1000,"size":21089,"sizeLabel":"20.6 KB","modified":"2026-07-07 09:27:42","content":"\n## 自动更新流程启动\n\n- `08:00:04` <span style=\"color:#2563eb;font-weight:700\">INFO</span> 运行范围: 全部流程\n- `08:00:04` <span style=\"color:#2563eb;font-weight:700\">INFO</span> CM China snapshot 已读取: latest_cm_china.csv.gz\n\n## 开始执行: 工作日数据\n\n- `08:00:04` <span style=\"color:#16a34a;font-weight:700\">OK</span> 工作日数据 执行完成\n\n\n## 开始执行: 航空\n\n- `08:00:52` <span style=\"color:#2563eb;font-weight:700\">INFO</span> 航空 输出\n\n```text\nGDP接口请求失败，使用本地缓存: GDP.csv\n500 Server Error: Internal Server Error for url: https://data.stats.gov.cn/dg/website/publicrelease/web/external/stream/esData\n```\n- `08:00:52` <span style=\"color:#16a34a;font-weight:700\">OK</span> 航空 执行完成，当前更新到: 2026-03-31\n\n\n## 开始执行: 地面交通\n\n- `09:19:26` <span style=\"color:#2563eb;font-weight:700\">INFO</span> 地面交通 输出\n\n```text\n更新完成: 拥堵延时指数:济南\n更新完成: 拥堵延时指数:泉州\n更新完成: 拥堵延时指数:郑州\n更新完成: 拥堵延时指数:贵阳\n更新完成: 拥堵延时指数:沈阳\n更新完成: 拥堵延时指数:金华\n更新完成: 拥堵延时指数:大连\n更新完成: 拥堵延时指数:徐州\n更新完成: 拥堵延时指数:合肥\n更新完成: 拥堵延时指数:扬州\n更新完成: 拥堵延时指数:哈尔滨\n更新完成: 拥堵延时指数:南通\n更新完成: 拥堵延时指数:长沙\n更新完成: 拥堵延时指数:重庆\n更新完成: 拥堵延时指数:珠海\n更新完成: 拥堵延时指数:嘉兴\n更新完成: 拥堵延时指数:昆明\n更新完成: 拥堵延时指数:惠州\n更新完成: 拥堵延时指数:厦门\n更新完成: 拥堵延时指数:长春\n更新完成: 拥堵延时指数:成都\n更新完成: 拥堵延时指数:西安\n更新完成: 拥堵延时指数:潍坊\n更新完成: 拥堵延时指数:绍兴\n更新完成: 拥堵延时指数:石家庄\n更新完成: 拥堵延时指数:天津\n更新完成: 拥堵延时指数:南京\n更新完成: 拥堵延时指数:福州\n更新完成: 拥堵延时指数:太原\n更新完成: 拥堵延时指数:常州\n更新完成: 拥堵延时指数:温州\n更新完成: 拥堵延时指数:南宁\n更新完成: 拥堵延时指数:台州\n更新完成: 拥堵延时指数:佛山\n更新完成: 拥堵延时指数:武汉\n更新完成: 拥堵延时指数:杭州\n更新完成: 拥堵延时指数:广州\n更新完成: 拥堵延时指数:中山\n更新完成: 拥堵延时指数:北京\n更新完成: 拥堵延时指数:苏州\n更新完成: 拥堵延时指数:深圳\n更新完成: 拥堵延时指数:青岛\n更新完成: 拥堵延时指数:东莞\n更新完成: 拥堵延时指数:宁波\n更新完成: 拥堵延时指数:上海\n更新完成: 拥堵延时指数:无锡\n更新完成: 拥堵延时指数:保定\n更新完成: 拥堵延时指数:大同\n更新完成: 拥堵延时指数:鄂尔多斯\n更新完成: 拥堵延时指数:兰州\n更新完成: 拥堵延时指数:洛阳\n更新完成: 拥堵延时指数:南昌\n更新完成: 拥堵延时指数:唐山\n更新完成: 拥堵延时指数:乌鲁木齐\n更新完成: 拥堵延时指数:中国香港\n更新完成: 拥堵延时指数:西宁\n更新完成: 拥堵延时指数:烟台\n更新完成: 拥堵延时指数:淄博\n更新完成: 拥堵延时指数:镇江\n更新完成: 拥堵延时指数:临沂\n更新完成: 拥堵延时指数:沧州\n更新完成: 拥堵延时指数:滁州\n更新完成: 拥堵延时指数:德阳\n更新完成: 拥堵延时指数:德州\n更新完成: 拥堵延时指数:赣州\n更新完成: 拥堵延时指数:桂林\n更新完成: 拥堵延时指数:海口\n更新完成: 拥堵延时指数:邯郸\n更新完成: 拥堵延时指数:衡阳\n更新完成: 拥堵延时指数:呼和浩特\n更新完成: 拥堵延时指数:湖州\n更新完成: 拥堵延时指数:淮安\n更新完成: 拥堵延时指数:济宁\n更新完成: 拥堵延时指数:江门\n更新完成: 拥堵延时指数:廊坊\n更新完成: 拥堵延时指数:连云港\n更新完成: 拥堵延时指数:柳州\n更新完成: 拥堵延时指数:茂名\n更新完成: 拥堵延时指数:绵阳\n更新完成: 拥堵延时指数:南充\n更新完成: 拥堵延时指数:南阳\n更新完成: 拥堵延时指数:秦皇岛\n更新完成: 拥堵延时指数:清远\n更新完成: 拥堵延时指数:三亚\n更新完成: 拥堵延时指数:汕头\n更新完成: 拥堵延时指数:韶关\n更新完成: 拥堵延时指数:泰安\n更新完成: 拥堵延时指数:泰州\n更新完成: 拥堵延时指数:芜湖\n更新完成: 拥堵延时指数:咸阳\n更新完成: 拥堵延时指数:新乡\n更新完成: 拥堵延时指数:邢台\n更新完成: 拥堵延时指数:宿迁\n更新完成: 拥堵延时指数:盐城\n更新完成: 拥堵延时指数:伊犁\n更新完成: 拥堵延时指数:银川\n更新完成: 拥堵延时指数:湛江\n更新完成: 拥堵延时指数:张家口\n更新完成: 拥堵延时指数:漳州\n更新完成: 拥堵延时指数:肇庆\n更新完成: 交通健康指数:济南\n更新完成: 交通健康指数:泉州\n更新完成: 交通健康指数:郑州\n更新完成: 交通健康指数:贵阳\n更新完成: 交通健康指数:沈阳\n更新完成: 交通健康指数:金华\n更新完成: 交通健康指数:大连\n更新完成: 交通健康指数:徐州\n更新完成: 交通健康指数:合肥\n更新完成: 交通健康指数:扬州\n更新完成: 交通健康指数:哈尔滨\n更新完成: 交通健康指数:南通\n更新完成: 交通健康指数:长沙\n更新完成: 交通健康指数:重庆\n更新完成: 交通健康指数:珠海\n更新完成: 交通健康指数:嘉兴\n更新完成: 交通健康指数:昆明\n更新完成: 交通健康指数:惠州\n更新完成: 交通健康指数:厦门\n更新完成: 交通健康指数:长春\n更新完成: 交通健康指数:成都\n更新完成: 交通健康指数:西安\n更新完成: 交通健康指数:潍坊\n更新完成: 交通健康指数:绍兴\n更新完成: 交通健康指数:石家庄\n更新完成: 交通健康指数:天津\n更新完成: 交通健康指数:南京\n更新完成: 交通健康指数:福州\n更新完成: 交通健康指数:太原\n更新完成: 交通健康指数:常州\n更新完成: 交通健康指数:温州\n更新完成: 交通健康指数:南宁\n更新完成: 交通健康指数:台州\n更新完成: 交通健康指数:佛山\n更新完成: 交通健康指数:武汉\n更新完成: 交通健康指数:杭州\n更新完成: 交通健康指数:广州\n更新完成: 交通健康指数:中山\n更新完成: 交通健康指数:北京\n更新完成: 交通健康指数:苏州\n更新完成: 交通健康指数:深圳\n更新完成: 交通健康指数:青岛\n更新完成: 交通健康指数:东莞\n更新完成: 交通健康指数:宁波\n更新完成: 交通健康指数:上海\n更新完成: 交通健康指数:无锡\n更新完成: 交通健康指数:保定\n更新完成: 交通健康指数:大同\n更新完成: 交通健康指数:鄂尔多斯\n更新完成: 交通健康指数:兰州\n更新完成: 交通健康指数:洛阳\n更新完成: 交通健康指数:南昌\n更新完成: 交通健康指数:唐山\n更新完成: 交通健康指数:乌鲁木齐\n更新完成: 交通健康指数:中国香港\n更新完成: 交通健康指数:西宁\n更新完成: 交通健康指数:烟台\n更新完成: 交通健康指数:淄博\n更新完成: 交通健康指数:镇江\n更新完成: 交通健康指数:临沂\n更新完成: 交通健康指数:沧州\n更新完成: 交通健康指数:滁州\n更新完成: 交通健康指数:德阳\n更新完成: 交通健康指数:德州\n更新完成: 交通健康指数:赣州\n更新完成: 交通健康指数:桂林\n更新完成: 交通健康指数:海口\n更新完成: 交通健康指数:邯郸\n更新完成: 交通健康指数:衡阳\n更新完成: 交通健康指数:呼和浩特\n更新完成: 交通健康指数:湖州\n更新完成: 交通健康指数:淮安\n更新完成: 交通健康指数:济宁\n更新完成: 交通健康指数:江门\n更新完成: 交通健康指数:廊坊\n更新完成: 交通健康指数:连云港\n更新完成: 交通健康指数:柳州\n更新完成: 交通健康指数:茂名\n更新完成: 交通健康指数:绵阳\n更新完成: 交通健康指数:南充\n更新完成: 交通健康指数:南阳\n更新完成: 交通健康指数:秦皇岛\n更新完成: 交通健康指数:清远\n更新完成: 交通健康指数:三亚\n更新完成: 交通健康指数:汕头\n更新完成: 交通健康指数:韶关\n更新完成: 交通健康指数:泰安\n更新完成: 交通健康指数:泰州\n更新完成: 交通健康指数:芜湖\n更新完成: 交通健康指数:咸阳\n更新完成: 交通健康指数:新乡\n更新完成: 交通健康指数:邢台\n更新完成: 交通健康指数:宿迁\n更新完成: 交通健康指数:盐城\n更新完成: 交通健康指数:伊犁\n更新完成: 交通健康指数:银川\n更新完成: 交通健康指数:湛江\n更新完成: 交通健康指数:张家口\n更新完成: 交通健康指数:漳州\n更新完成: 交通健康指数:肇庆\n更新完成: 平均速度:济南\n更新完成: 平均速度:泉州\n更新完成: 平均速度:郑州\n更新完成: 平均速度:贵阳\n更新完成: 平均速度:沈阳\n更新完成: 平均速度:金华\n更新完成: 平均速度:大连\n更新完成: 平均速度:徐州\n更新完成: 平均速度:合肥\n更新完成: 平均速度:扬州\n更新完成: 平均速度:哈尔滨\n更新完成: 平均速度:南通\n更新完成: 平均速度:长沙\n更新完成: 平均速度:重庆\n更新完成: 平均速度:珠海\n更新完成: 平均速度:嘉兴\n更新完成: 平均速度:昆明\n更新完成: 平均速度:惠州\n更新完成: 平均速度:厦门\n更新完成: 平均速度:长春\n更新完成: 平均速度:成都\n更新完成: 平均速度:西安\n更新完成: 平均速度:潍坊\n更新完成: 平均速度:绍兴\n更新完成: 平均速度:石家庄\n更新完成: 平均速度:天津\n更新完成: 平均速度:南京\n更新完成: 平均速度:福州\n更新完成: 平均速度:太原\n更新完成: 平均速度:常州\n更新完成: 平均速度:温州\n更新完成: 平均速度:南宁\n更新完成: 平均速度:台州\n更新完成: 平均速度:佛山\n更新完成: 平均速度:武汉\n更新完成: 平均速度:杭州\n更新完成: 平均速度:广州\n更新完成: 平均速度:中山\n更新完成: 平均速度:北京\n更新完成: 平均速度:苏州\n更新完成: 平均速度:深圳\n更新完成: 平均速度:青岛\n更新完成: 平均速度:东莞\n更新完成: 平均速度:宁波\n更新完成: 平均速度:上海\n更新完成: 平均速度:无锡\n更新完成: 平均速度:保定\n更新完成: 平均速度:大同\n更新完成: 平均速度:鄂尔多斯\n更新完成: 平均速度:兰州\n更新完成: 平均速度:洛阳\n更新完成: 平均速度:南昌\n更新完成: 平均速度:唐山\n更新完成: 平均速度:乌鲁木齐\n更新完成: 平均速度:中国香港\n更新完成: 平均速度:西宁\n更新完成: 平均速度:烟台\n更新完成: 平均速度:淄博\n更新完成: 平均速度:镇江\n更新完成: 平均速度:临沂\n更新完成: 平均速度:沧州\n更新完成: 平均速度:滁州\n更新完成: 平均速度:德阳\n更新完成: 平均速度:德州\n更新完成: 平均速度:赣州\n更新完成: 平均速度:桂林\n更新完成: 平均速度:海口\n更新完成: 平均速度:邯郸\n更新完成: 平均速度:衡阳\n更新完成: 平均速度:呼和浩特\n更新完成: 平均速度:湖州\n更新完成: 平均速度:淮安\n更新完成: 平均速度:济宁\n更新完成: 平均速度:江门\n更新完成: 平均速度:廊坊\n更新完成: 平均速度:连云港\n更新完成: 平均速度:柳州\n更新完成: 平均速度:茂名\n更新完成: 平均速度:绵阳\n更新完成: 平均速度:南充\n更新完成: 平均速度:南阳\n更新完成: 平均速度:秦皇岛\n更新完成: 平均速度:清远\n更新完成: 平均速度:三亚\n更新完成: 平均速度:汕头\n更新完成: 平均速度:韶关\n更新完成: 平均速度:泰安\n更新完成: 平均速度:泰州\n更新完成: 平均速度:芜湖\n更新完成: 平均速度:咸阳\n更新完成: 平均速度:新乡\n更新完成: 平均速度:邢台\n更新完成: 平均速度:宿迁\n更新完成: 平均速度:盐城\n更新完成: 平均速度:伊犁\n更新完成: 平均速度:银川\n更新完成: 平均速度:湛江\n更新完成: 平均速度:张家口\n更新完成: 平均速度:漳州\n更新完成: 平均速度:肇庆\n汇总完成: china_交通健康指数.csv\n汇总完成: china_拥堵延时指数.csv\n汇总完成: china_平均速度.csv\n```\n- `09:19:26` <span style=\"color:#16a34a;font-weight:700\">OK</span> 地面交通 执行完成，当前更新到: 2026-05-31\n\n\n## 开始执行: 工业\n\n- `09:27:27` <span style=\"color:#2563eb;font-weight:700\">INFO</span> 工业 输出\n\n```text\n[1/60] 铁矿石原矿量\n  failed -> 铁矿石原矿量: Expecting value: line 1 column 1 (char 0)\n[2/60] 磷矿石\n  saved -> 磷矿石.csv\n[3/60] 原盐\n  failed -> 原盐: Expecting value: line 1 column 1 (char 0)\n[4/60] 成品糖\n  failed -> 成品糖: Expecting value: line 1 column 1 (char 0)\n[5/60] 饮料\n  failed -> 饮料: Expecting value: line 1 column 1 (char 0)\n[6/60] 纱\n  failed -> 纱: Expecting value: line 1 column 1 (char 0)\n[7/60] 布\n  failed -> 布: Expecting value: line 1 column 1 (char 0)\n[8/60] 机制纸及纸板\n  failed -> 机制纸及纸板: Expecting value: line 1 column 1 (char 0)\n[9/60] 新闻纸\n  failed -> 新闻纸: Expecting value: line 1 column 1 (char 0)\n[10/60] 硫酸\n  failed -> 硫酸: Expecting value: line 1 column 1 (char 0)\n[11/60] 烧碱 (折100%) \n  failed -> 烧碱 (折100%) : Expecting value: line 1 column 1 (char 0)\n[12/60] 纯碱 (碳酸钠) \n  failed -> 纯碱 (碳酸钠) : Expecting value: line 1 column 1 (char 0)\n[13/60] 农用氮磷钾化肥 (折纯) \n  failed -> 农用氮磷钾化肥 (折纯) : Expecting value: line 1 column 1 (char 0)\n[14/60] 化学农药原药\n  failed -> 化学农药原药: Expecting value: line 1 column 1 (char 0)\n[15/60] 乙烯\n  failed -> 乙烯: Expecting value: line 1 column 1 (char 0)\n[16/60] 初级形态的塑料\n  failed -> 初级形态的塑料: Expecting value: line 1 column 1 (char 0)\n[17/60] 合成洗涤剂\n  failed -> 合成洗涤剂: Expecting value: line 1 column 1 (char 0)\n[18/60] 化学纤维\n  failed -> 化学纤维: Expecting value: line 1 column 1 (char 0)\n[19/60] 塑料制品\n  failed -> 塑料制品: Expecting value: line 1 column 1 (char 0)\n[20/60] 水泥\n  failed -> 水泥: Expecting value: line 1 column 1 (char 0)\n[21/60] 平板玻璃\n  failed -> 平板玻璃: Expecting value: line 1 column 1 (char 0)\n[22/60] 生铁\n  failed -> 生铁: Expecting value: line 1 column 1 (char 0)\n[23/60] 粗钢\n  failed -> 粗钢: Expecting value: line 1 column 1 (char 0)\n[24/60] 钢材\n  failed -> 钢材: Expecting value: line 1 column 1 (char 0)\n[25/60] 十种有色金属\n  failed -> 十种有色金属: Expecting value: line 1 column 1 (char 0)\n[26/60] 氧化铝\n  failed -> 氧化铝: Expecting value: line 1 column 1 (char 0)\n[27/60] 铜材\n  failed -> 铜材: Expecting value: line 1 column 1 (char 0)\n[28/60] 铝材\n  failed -> 铝材: Expecting value: line 1 column 1 (char 0)\n[29/60] 工业锅炉\n  failed -> 工业锅炉: Expecting value: line 1 column 1 (char 0)\n[30/60] 发动机\n  failed -> 发动机: Expecting value: line 1 column 1 (char 0)\n[31/60] 金属切削机床\n  failed -> 金属切削机床: Expecting value: line 1 column 1 (char 0)\n[32/60] 电动手提式工具\n  failed -> 电动手提式工具: Expecting value: line 1 column 1 (char 0)\n[33/60] 金属冶炼设备\n  failed -> 金属冶炼设备: Expecting value: line 1 column 1 (char 0)\n[34/60] 水泥专用设备\n  failed -> 水泥专用设备: Expecting value: line 1 column 1 (char 0)\n[35/60] 包装专用设备\n  failed -> 包装专用设备: Expecting value: line 1 column 1 (char 0)\n[36/60] 大型拖拉机\n  failed -> 大型拖拉机: Expecting value: line 1 column 1 (char 0)\n[37/60] 中型拖拉机\n  failed -> 中型拖拉机: Expecting value: line 1 column 1 (char 0)\n[38/60] 小型拖拉机\n  failed -> 小型拖拉机: Expecting value: line 1 column 1 (char 0)\n[39/60] 大气污染防治设备\n  failed -> 大气污染防治设备: Expecting value: line 1 column 1 (char 0)\n[40/60] 铁路机车\n  failed -> 铁路机车: Expecting value: line 1 column 1 (char 0)\n[41/60] 汽车\n  failed -> 汽车: Expecting value: line 1 column 1 (char 0)\n[42/60] 新能源汽车\n  failed -> 新能源汽车: Expecting value: line 1 column 1 (char 0)\n[43/60] 民用钢质船舶\n  failed -> 民用钢质船舶: Expecting value: line 1 column 1 (char 0)\n[44/60] 发电设备\n  failed -> 发电设备: Expecting value: line 1 column 1 (char 0)\n[45/60] 交流电动机\n  failed -> 交流电动机: Expecting value: line 1 column 1 (char 0)\n[46/60] 家用洗衣机\n  failed -> 家用洗衣机: Expecting value: line 1 column 1 (char 0)\n[47/60] 家用电冰箱\n  failed -> 家用电冰箱: Expecting value: line 1 column 1 (char 0)\n[48/60] 家用冷柜\n  failed -> 家用冷柜: Expecting value: line 1 column 1 (char 0)\n[49/60] 房间空气调节器\n  failed -> 房间空气调节器: Expecting value: line 1 column 1 (char 0)\n[50/60] 程控交换机\n  failed -> 程控交换机: Expecting value: line 1 column 1 (char 0)\n[51/60] 传真机\n  failed -> 传真机: Expecting value: line 1 column 1 (char 0)\n[52/60] 移动通信基站设备\n  failed -> 移动通信基站设备: Expecting value: line 1 column 1 (char 0)\n[53/60] 移动通信手持机\n  failed -> 移动通信手持机: Expecting value: line 1 column 1 (char 0)\n[54/60] 智能手机\n  failed -> 智能手机: Expecting value: line 1 column 1 (char 0)\n[55/60] 电子计算机整机\n  failed -> 电子计算机整机: Expecting value: line 1 column 1 (char 0)\n[56/60] 微型计算机设备\n  failed -> 微型计算机设备: Expecting value: line 1 column 1 (char 0)\n[57/60] 集成电路\n  failed -> 集成电路: Expecting value: line 1 column 1 (char 0)\n[58/60] 彩色电视机\n  failed -> 彩色电视机: Expecting value: line 1 column 1 (char 0)\n[59/60] 电工仪器仪表\n  failed -> 电工仪器仪表: Expecting value: line 1 column 1 (char 0)\n[60/60] 复印和胶版印制设备\n  failed -> 复印和胶版印制设备: Expecting value: line 1 column 1 (char 0)\n```\n- `09:27:27` <span style=\"color:#16a34a;font-weight:700\">OK</span> 工业 执行完成，当前更新到: 2026-05-31\n\n\n## 开始执行: 电力\n\n- `09:27:30` <span style=\"color:#dc2626;font-weight:700\">ERROR</span> 电力 执行失败: Expecting value: line 1 column 1 (char 0)\n- `09:27:30` <span style=\"color:#dc2626;font-weight:700\">ERROR</span> 错误堆栈如下\n\n```text\nTraceback (most recent call last):\n  File \"models.py\", line 971, in json\n    return complexjson.loads(self.text, **kwargs)\n  File \"__init__.py\", line 514, in loads\n    return _default_decoder.decode(s)\n  File \"decoder.py\", line 386, in decode\n    obj, end = self.raw_decode(s)\n  File \"decoder.py\", line 416, in raw_decode\n    return self.scan_once(s, idx=_w(s, idx).end())\nsimplejson.errors.JSONDecodeError: Expecting value: line 1 column 1 (char 0)\n\nDuring handling of the above exception, another exception occurred:\n\nTraceback (most recent call last):\n  File \"all_process.py\", line 113, in execute_workflow\n    workflow_module.main()\n  File \"power.py\", line 17, in main\n    pc.main()\n  File \"power_craw.py\", line 18, in main\n    craw()\n  File \"power_craw.py\", line 22, in craw\n    get_power_json(file_path, cumulative=False)\n  File \"power_craw.py\", line 39, in get_power_json\n    df = af.get_stats_json(\n  File \"global_function.py\", line 467, in get_stats_json\n    result = post_stats(payload)\n  File \"global_function.py\", line 465, in post_stats\n    return resp.json()\n  File \"models.py\", line 975, in json\n    raise RequestsJSONDecodeError(e.msg, e.doc, e.pos)\nrequests.exceptions.JSONDecodeError: Expecting value: line 1 column 1 (char 0)\n```\n- `09:27:30` <span style=\"color:#dc2626;font-weight:700\">ERROR</span> 电力 异常结束\n\n\n## 开始执行: 居民\n\n- `09:27:31` <span style=\"color:#16a34a;font-weight:700\">OK</span> 居民 执行完成，当前更新到: 2026-05-31\n\n\n## 开始执行: 总表汇总\n\n- `09:27:39` <span style=\"color:#16a34a;font-weight:700\">OK</span> 总表汇总 执行完成，当前更新到: 2026-03-31\n\n\n## CM China 发布检查\n\n- `09:27:40` <span style=\"color:#2563eb;font-weight:700\">INFO</span> CM China snapshot 对比: 新增 0 行 | 删除 0 行 | 数值变化 0 行\n- `09:27:40` <span style=\"color:#16a34a;font-weight:700\">OK</span> 跳过发布: CM China 总表无变化\n\n## 跳过执行: 自动上传\n\n- `09:27:40` <span style=\"color:#16a34a;font-weight:700\">OK</span> 跳过上传: CM China 总表无变化\n\n\n## 跳过执行: 图片生成\n\n- `09:27:40` <span style=\"color:#16a34a;font-weight:700\">OK</span> 跳过图片: CM China 总表无变化\n\n\n## 开始执行: 欧洲数据整理\n\n- `09:27:42` <span style=\"color:#16a34a;font-weight:700\">OK</span> 欧洲数据整理 执行完成\n\n\n## 本次运行耗时: 1小时 27分钟 38秒\n"}